{"IdentificationComponent": {"m_name": "In a wide canyon"}, "InventoryComponent": {}, "LocalMessageComponent": {}, "RoomComponent": {"m_code": "SkoleCracks_0_29_28", "m_description": "The canyon turns here in a huge rippling bulge of rock and dust. smooth gravel sifts across the canyon bed.   "}, "m_doors": [{"code": "SkoleCracks_0_28_28", "dir": "w", "status": "open"}, {"code": "SkoleCracks_0_28_29", "dir": "sw", "status": "open"}, {"code": "SkoleCracks_0_29_27", "dir": "n", "status": "open"}, {"code": "SkoleCracks_0_29_29", "dir": "s", "status": "open"}]}