{"IdentificationComponent": {"m_name": "In a Clearing"}, "InventoryComponent": {}, "LocalMessageComponent": {}, "RoomComponent": {"m_code": "SkoleCracks_0_18_5", "m_description": "You move through an open clearing. High above your head, a crusty line of white and brown marks the high water mark on the now bone dry rock.   "}, "m_doors": [{"code": "SkoleCracks_0_17_4", "dir": "nw", "status": "open"}, {"code": "SkoleCracks_0_17_5", "dir": "w", "status": "open"}, {"code": "SkoleCracks_0_19_6", "dir": "se", "status": "open"}]}