{"IdentificationComponent": {"m_name": "On a Hillside"}, "InventoryComponent": {}, "LocalMessageComponent": {}, "RoomComponent": {"m_code": "Forest1_0_6_25", "m_description": "The landscape slopes gently upwards here. Dense brush makes the passage slow.   Not far away, the brush and trees thicken as the forest grows deeper."}, "m_doors": [{"code": "Forest1_0_5_25", "dir": "w", "status": "open"}, {"code": "Forest1_0_6_24", "dir": "n", "status": "open"}, {"code": "Forest1_0_7_24", "dir": "ne", "status": "open"}]}