{"IdentificationComponent": {"m_name": "On a Hillside"}, "InventoryComponent": {}, "LocalMessageComponent": {}, "RoomComponent": {"m_code": "Forest1_0_19_13", "m_description": "Terraced steps lead up a gentle hill. A solitary oak tree stands like a sentinel.   Nearby, the landscape opens into a grassy clearing."}, "m_doors": [{"code": "Forest1_0_18_13", "dir": "w", "status": "open"}, {"code": "Forest1_0_18_14", "dir": "sw", "status": "open"}, {"code": "Forest1_0_19_14", "dir": "s", "status": "open"}, {"code": "Forest1_0_20_12", "dir": "ne", "status": "open"}]}