{"IdentificationComponent": {"m_name": "Atop a knoll"}, "InventoryComponent": {}, "LocalMessageComponent": {}, "RoomComponent": {"m_code": "Forest1_0_13_17", "m_description": "You stand atop a rocky hill. A  pile of stones marks the summit of the low hill.   "}, "m_doors": [{"code": "Forest1_0_12_17", "dir": "w", "status": "open"}, {"code": "Forest1_0_12_18", "dir": "sw", "status": "open"}, {"code": "Forest1_0_14_16", "dir": "ne", "status": "open"}, {"code": "Forest1_0_14_18", "dir": "se", "status": "open"}]}