{"IdentificationComponent": {"m_name": "Within the Stone Forest"}, "InventoryComponent": {}, "LocalMessageComponent": {}, "RoomComponent": {"m_code": "Cave_0_21_21", "m_description": "You step through the long forgotten forest, leaves flaking quietly underfoot. A few blades of dark green crystals grow between the tree roots. "}, "m_doors": [{"code": "Cave_0_20_21", "dir": "w", "status": "open"}, {"code": "Cave_0_22_20", "dir": "ne", "status": "open"}, {"code": "Cave_0_22_22", "dir": "se", "status": "open"}]}